correlation_py-0.2.0.dist-info/METADATA
correlation_py-0.2.0.dist-info/WHEEL
correlation_py-0.2.0.dist-info/licenses/LICENSE
correlation_py/__init__.py
correlation_py/_internal.cpython-312-x86_64-linux-gnu.so
correlation_py/correlation.py
correlation_py/result.py
correlation_py/utils.py
correlation_py-0.2.0.dist-info/RECORD
