Metadata-Version: 2.4
Name: correlation_py
Version: 0.2.0
Classifier: Programming Language :: Rust
Classifier: Programming Language :: Python :: Implementation :: CPython
Classifier: Programming Language :: Python :: Implementation :: PyPy
Requires-Dist: numpy
Requires-Dist: stim
Requires-Dist: maturin ; extra == 'dev'
Requires-Dist: pytest ; extra == 'dev'
Requires-Dist: ruff ; extra == 'dev'
Provides-Extra: dev
License-File: LICENSE
Summary: High order correlation analysis of error models.
Author: Yiming Zhang
Requires-Python: >=3.7
